scenecut_extractor/__init__.py
scenecut_extractor/__main__.py
scenecut_extractor/_log.py
scenecut_extractor/_scenecut_extractor.py
scenecut_extractor/py.typed
scenecut_extractor-0.9.0.dist-info/licenses/LICENSE.md
scenecut_extractor-0.9.0.dist-info/WHEEL
scenecut_extractor-0.9.0.dist-info/entry_points.txt
scenecut_extractor-0.9.0.dist-info/METADATA
scenecut_extractor-0.9.0.dist-info/RECORD
