Metadata-Version: 2.4
Name: scenecut-extractor
Version: 0.9.0
Summary: Get scenecuts from a video file using ffmpeg
Author: Werner Robitza
Author-email: Werner Robitza <werner.robitza@gmail.com>
License-Expression: MIT
License-File: LICENSE.md
Classifier: Development Status :: 4 - Beta
Classifier: Intended Audience :: Developers
Classifier: Topic :: Multimedia :: Video
Classifier: Programming Language :: Python :: 3
Classifier: Programming Language :: Python :: 3.9
Classifier: Programming Language :: Python :: 3.10
Classifier: Programming Language :: Python :: 3.11
Classifier: Programming Language :: Python :: 3.12
Classifier: Programming Language :: Python :: 3.13
Classifier: Programming Language :: Python :: 3.14
Requires-Dist: tqdm>=4.38.0
Requires-Dist: ffmpeg-progress-yield
Requires-Python: >=3.9
Project-URL: Homepage, https://github.com/slhck/scenecut-extractor
Project-URL: Repository, https://github.com/slhck/scenecut-extractor
